{
  "slug": "00007_human",
  "name": "Eowyn the Wanderer",
  "race": "human",
  "seed": 7,
  "turn": 454,
  "max_floor": 2,
  "level": 2,
  "hp": -2,
  "max_hp": 40,
  "gold": 904,
  "kills": 42,
  "alive": false,
  "status": "dead",
  "status_reason": "",
  "death_cause": "defeated by poison",
  "started": "2026-05-18T20:27:28+00:00",
  "moves_total": 205,
  "moves_revisit": 159,
  "wasted_pct": 77.6,
  "floor_changes": 1,
  "warp_changes": 1,
  "warp_accepts": 0,
  "warp_forced": 1,
  "warp_pct": 100.0,
  "monsters_total": 58,
  "monsters_killed": 42,
  "kill_pct": 72.4,
  "xp_pool": 628,
  "xp_earned": 336,
  "xp_pct": 53.5,
  "chests_total": 14,
  "boons_total": 24,
  "loop_episode_count": 0,
  "loop_turns_total": 0
}