{
  "slug": "00013_dwarf",
  "name": "Dori of Erebor",
  "race": "dwarf",
  "seed": 13,
  "turn": 3000,
  "max_floor": 6,
  "level": 5,
  "hp": 115,
  "max_hp": 115,
  "gold": 177,
  "kills": 109,
  "alive": true,
  "death_cause": "\u2014",
  "started": "2026-05-17T13:47:38+00:00",
  "moves_total": 473,
  "moves_revisit": 249,
  "wasted_pct": 52.6,
  "floor_changes": 6,
  "warp_changes": 0,
  "warp_accepts": 0,
  "warp_forced": 0,
  "warp_pct": 0.0,
  "monsters_total": 140,
  "monsters_killed": 109,
  "kill_pct": 77.9,
  "xp_pool": 3848,
  "xp_earned": 2748,
  "xp_pct": 71.4,
  "chests_total": 35,
  "boons_total": 62
}