{
  "slug": "00013_human",
  "name": "Anborn the Brave",
  "race": "human",
  "seed": 13,
  "turn": 1926,
  "max_floor": 6,
  "level": 6,
  "hp": -7,
  "max_hp": 88,
  "gold": 845,
  "kills": 195,
  "alive": false,
  "death_cause": "defeated by UNDEAD WRAITH",
  "started": "2026-05-18T02:08:23+00:00",
  "moves_total": 1105,
  "moves_revisit": 827,
  "wasted_pct": 74.8,
  "floor_changes": 13,
  "warp_changes": 0,
  "warp_accepts": 0,
  "warp_forced": 0,
  "warp_pct": 0.0,
  "monsters_total": 195,
  "monsters_killed": 195,
  "kill_pct": 100.0,
  "xp_pool": 5192,
  "xp_earned": 5192,
  "xp_pct": 100.0,
  "chests_total": 42,
  "boons_total": 75
}