{
  "slug": "00023_human",
  "name": "Beorn the Wise",
  "race": "human",
  "seed": 23,
  "turn": 990,
  "max_floor": 5,
  "level": 5,
  "hp": 13,
  "max_hp": 72,
  "gold": 1251,
  "kills": 110,
  "alive": true,
  "legit_alive": false,
  "legit_reason": "loop (68% wasted)",
  "death_cause": "\u2014",
  "started": "2026-05-18T12:07:01+00:00",
  "moves_total": 481,
  "moves_revisit": 327,
  "wasted_pct": 68.0,
  "floor_changes": 6,
  "warp_changes": 0,
  "warp_accepts": 0,
  "warp_forced": 0,
  "warp_pct": 0.0,
  "monsters_total": 118,
  "monsters_killed": 110,
  "kill_pct": 93.2,
  "xp_pool": 3026,
  "xp_earned": 2536,
  "xp_pct": 83.8,
  "chests_total": 28,
  "boons_total": 47
}