{
  "slug": "00047_dwarf",
  "name": "Durin Deepdelver",
  "race": "dwarf",
  "seed": 47,
  "turn": 739,
  "max_floor": 4,
  "level": 2,
  "hp": -10,
  "max_hp": 80,
  "gold": 524,
  "kills": 52,
  "alive": false,
  "status": "dead",
  "status_reason": "",
  "death_cause": "defeated by ELITE UNDEAD WRAITH",
  "started": "2026-05-18T16:33:49+00:00",
  "moves_total": 422,
  "moves_revisit": 303,
  "wasted_pct": 71.8,
  "floor_changes": 2,
  "warp_changes": 1,
  "warp_accepts": 0,
  "warp_forced": 1,
  "warp_pct": 50.0,
  "monsters_total": 103,
  "monsters_killed": 52,
  "kill_pct": 50.5,
  "xp_pool": 1976,
  "xp_earned": 1304,
  "xp_pct": 66.0,
  "chests_total": 21,
  "boons_total": 36,
  "loop_episode_count": 1,
  "loop_turns_total": 67
}