{
  "slug": "00071_dwarf",
  "name": "Bifur the Mighty",
  "race": "dwarf",
  "seed": 71,
  "turn": 4148,
  "max_floor": 4,
  "level": 4,
  "hp": 0,
  "max_hp": 104,
  "gold": 141,
  "kills": 114,
  "alive": false,
  "status": "dead",
  "status_reason": "",
  "death_cause": "starvation",
  "started": "2026-05-18T19:47:18+00:00",
  "moves_total": 3434,
  "moves_revisit": 3268,
  "wasted_pct": 95.2,
  "floor_changes": 3,
  "warp_changes": 0,
  "warp_accepts": 0,
  "warp_forced": 0,
  "warp_pct": 0.0,
  "monsters_total": 114,
  "monsters_killed": 114,
  "kill_pct": 100.0,
  "xp_pool": 2710,
  "xp_earned": 2710,
  "xp_pct": 100.0,
  "chests_total": 28,
  "boons_total": 50,
  "loop_episode_count": 1,
  "loop_turns_total": 50
}