{
  "slug": "00173_human",
  "name": "S173-H",
  "race": "human",
  "seed": 173,
  "turn": 1143,
  "max_floor": 21,
  "level": 14,
  "hp": -17,
  "max_hp": 168,
  "gold": 4,
  "kills": 7,
  "alive": false,
  "status": "dead",
  "status_reason": "",
  "death_cause": "defeated by Savage Iron Golem",
  "started": "2026-05-21T13:17:55+00:00",
  "moves_total": 475,
  "moves_revisit": 175,
  "wasted_pct": 36.8,
  "floor_changes": 6,
  "warp_changes": 1,
  "warp_accepts": 0,
  "warp_forced": 1,
  "warp_pct": 16.7,
  "monsters_total": 122,
  "monsters_killed": 7,
  "kill_pct": 5.7,
  "xp_pool": 90316,
  "xp_earned": 11144,
  "xp_pct": 12.3,
  "chests_total": 49,
  "boons_total": 90,
  "loop_episode_count": 0,
  "loop_turns_total": 0
}