{
  "slug": "00314_elf",
  "name": "Galadhrim the Pathfinder",
  "race": "elf",
  "seed": 314,
  "turn": 535,
  "max_floor": 3,
  "level": 2,
  "hp": 0,
  "max_hp": 42,
  "gold": 266,
  "kills": 60,
  "alive": false,
  "status": "dead",
  "status_reason": "",
  "death_cause": "starvation",
  "started": "2026-05-18T15:15:47+00:00",
  "moves_total": 239,
  "moves_revisit": 138,
  "wasted_pct": 57.7,
  "floor_changes": 2,
  "warp_changes": 0,
  "warp_accepts": 0,
  "warp_forced": 0,
  "warp_pct": 0.0,
  "monsters_total": 66,
  "monsters_killed": 60,
  "kill_pct": 90.9,
  "xp_pool": 1080,
  "xp_earned": 840,
  "xp_pct": 77.8,
  "chests_total": 21,
  "boons_total": 36,
  "loop_episode_count": 0,
  "loop_turns_total": 0
}