{
  "slug": "00333_human",
  "name": "Eomer of the White City",
  "race": "human",
  "seed": 333,
  "turn": 1366,
  "max_floor": 3,
  "level": 3,
  "hp": 0,
  "max_hp": 50,
  "gold": 616,
  "kills": 106,
  "alive": false,
  "status": "dead",
  "status_reason": "",
  "death_cause": "starvation",
  "started": "2026-05-18T19:19:19+00:00",
  "moves_total": 815,
  "moves_revisit": 700,
  "wasted_pct": 85.9,
  "floor_changes": 2,
  "warp_changes": 0,
  "warp_accepts": 0,
  "warp_forced": 0,
  "warp_pct": 0.0,
  "monsters_total": 106,
  "monsters_killed": 106,
  "kill_pct": 100.0,
  "xp_pool": 1328,
  "xp_earned": 1328,
  "xp_pct": 100.0,
  "chests_total": 21,
  "boons_total": 35,
  "loop_episode_count": 0,
  "loop_turns_total": 0
}