{
  "slug": "01234_dwarf",
  "name": "Thorin of Belegost",
  "race": "dwarf",
  "seed": 1234,
  "turn": 1505,
  "max_floor": 4,
  "level": 3,
  "hp": 0,
  "max_hp": 111,
  "gold": 1371,
  "kills": 75,
  "alive": false,
  "status": "dead",
  "status_reason": "",
  "death_cause": "starvation",
  "started": "2026-05-18T17:43:11+00:00",
  "moves_total": 690,
  "moves_revisit": 502,
  "wasted_pct": 72.8,
  "floor_changes": 3,
  "warp_changes": 2,
  "warp_accepts": 0,
  "warp_forced": 2,
  "warp_pct": 66.7,
  "monsters_total": 90,
  "monsters_killed": 75,
  "kill_pct": 83.3,
  "xp_pool": 2216,
  "xp_earned": 1702,
  "xp_pct": 76.8,
  "chests_total": 28,
  "boons_total": 47,
  "loop_episode_count": 0,
  "loop_turns_total": 0
}