{
  "slug": "01337_dwarf",
  "name": "Durin Stonefoot",
  "race": "dwarf",
  "seed": 1337,
  "turn": 1530,
  "max_floor": 4,
  "level": 5,
  "hp": 0,
  "max_hp": 104,
  "gold": 1301,
  "kills": 129,
  "alive": false,
  "status": "dead",
  "status_reason": "",
  "death_cause": "starvation",
  "started": "2026-05-18T14:06:34+00:00",
  "moves_total": 928,
  "moves_revisit": 617,
  "wasted_pct": 66.5,
  "floor_changes": 6,
  "warp_changes": 0,
  "warp_accepts": 0,
  "warp_forced": 0,
  "warp_pct": 0.0,
  "monsters_total": 129,
  "monsters_killed": 129,
  "kill_pct": 100.0,
  "xp_pool": 3188,
  "xp_earned": 3188,
  "xp_pct": 100.0,
  "chests_total": 28,
  "boons_total": 48
}