{
  "slug": "01500_dwarf",
  "name": "Thror Stonebreaker",
  "race": "dwarf",
  "seed": 1500,
  "turn": 1135,
  "max_floor": 8,
  "level": 6,
  "hp": -23,
  "max_hp": 114,
  "gold": 475,
  "kills": 124,
  "alive": false,
  "death_cause": "defeated by UNDEAD LICH",
  "started": "2026-05-18T08:59:51+00:00",
  "moves_total": 478,
  "moves_revisit": 237,
  "wasted_pct": 49.6,
  "floor_changes": 6,
  "warp_changes": 0,
  "warp_accepts": 0,
  "warp_forced": 0,
  "warp_pct": 0.0,
  "monsters_total": 155,
  "monsters_killed": 124,
  "kill_pct": 80.0,
  "xp_pool": 8148,
  "xp_earned": 4038,
  "xp_pct": 49.6,
  "chests_total": 49,
  "boons_total": 86
}