{
  "slug": "02025_elf",
  "name": "Voronwe the Quenya-tongued",
  "race": "elf",
  "seed": 2025,
  "turn": 810,
  "max_floor": 3,
  "level": 3,
  "hp": -10,
  "max_hp": 44,
  "gold": 410,
  "kills": 102,
  "alive": false,
  "status": "dead",
  "status_reason": "",
  "death_cause": "defeated by ELITE UNDEAD WRAITH",
  "started": "2026-05-18T21:23:14+00:00",
  "moves_total": 272,
  "moves_revisit": 111,
  "wasted_pct": 40.8,
  "floor_changes": 2,
  "warp_changes": 1,
  "warp_accepts": 1,
  "warp_forced": 0,
  "warp_pct": 50.0,
  "monsters_total": 102,
  "monsters_killed": 102,
  "kill_pct": 100.0,
  "xp_pool": 1406,
  "xp_earned": 896,
  "xp_pct": 63.7,
  "chests_total": 21,
  "boons_total": 35,
  "loop_episode_count": 0,
  "loop_turns_total": 0
}