{
  "slug": "09001_human",
  "name": "Isildur II",
  "race": "human",
  "seed": 9001,
  "turn": 570,
  "max_floor": 3,
  "level": 3,
  "hp": 0,
  "max_hp": 52,
  "gold": 275,
  "kills": 79,
  "alive": false,
  "death_cause": "starvation",
  "started": "2026-05-16T16:04:16+00:00",
  "moves_total": 203,
  "moves_revisit": 103,
  "wasted_pct": 50.7,
  "floor_changes": 2,
  "warp_changes": 0,
  "warp_accepts": 0,
  "warp_forced": 0,
  "warp_pct": 0.0,
  "monsters_total": 98,
  "monsters_killed": 79,
  "kill_pct": 80.6,
  "xp_pool": 1446,
  "xp_earned": 1184,
  "xp_pct": 81.9,
  "chests_total": 21,
  "boons_total": 37
}