{
  "slug": "27182_dwarf",
  "name": "Fili the Stout",
  "race": "dwarf",
  "seed": 27182,
  "turn": 2235,
  "max_floor": 8,
  "level": 7,
  "hp": 0,
  "max_hp": 124,
  "gold": 1763,
  "kills": 196,
  "alive": false,
  "status": "dead",
  "status_reason": "",
  "death_cause": "starvation",
  "started": "2026-05-18T21:23:24+00:00",
  "moves_total": 1228,
  "moves_revisit": 843,
  "wasted_pct": 68.6,
  "floor_changes": 13,
  "warp_changes": 4,
  "warp_accepts": 0,
  "warp_forced": 4,
  "warp_pct": 30.8,
  "monsters_total": 196,
  "monsters_killed": 196,
  "kill_pct": 100.0,
  "xp_pool": 10636,
  "xp_earned": 10636,
  "xp_pct": 100.0,
  "chests_total": 49,
  "boons_total": 78,
  "loop_episode_count": 3,
  "loop_turns_total": 338
}