{
  "slug": "31415_elf",
  "name": "Galadriel the Quenya-tongued",
  "race": "elf",
  "seed": 31415,
  "turn": 239,
  "max_floor": 2,
  "level": 1,
  "hp": -5,
  "max_hp": 28,
  "gold": 453,
  "kills": 11,
  "alive": false,
  "status": "dead",
  "status_reason": "",
  "death_cause": "lethal pool trap",
  "started": "2026-05-18T15:16:16+00:00",
  "moves_total": 116,
  "moves_revisit": 98,
  "wasted_pct": 84.5,
  "floor_changes": 1,
  "warp_changes": 0,
  "warp_accepts": 0,
  "warp_forced": 0,
  "warp_pct": 0.0,
  "monsters_total": 70,
  "monsters_killed": 11,
  "kill_pct": 15.7,
  "xp_pool": 748,
  "xp_earned": 138,
  "xp_pct": 18.4,
  "chests_total": 14,
  "boons_total": 25,
  "loop_episode_count": 0,
  "loop_turns_total": 0
}